tripo3d/__init__.py
tripo3d/client.py
tripo3d/exceptions.py
tripo3d/geo_utils.py
tripo3d/models.py
tripo3d/client_impl/__init__.py
tripo3d/client_impl/aiohttp_client_impl.py
tripo3d/client_impl/base_client.py
tripo3d/client_impl/legacy_client_impl.py
tripo3d-0.3.10.dist-info/licenses/LICENSE
tripo3d-0.3.10.dist-info/METADATA
tripo3d-0.3.10.dist-info/WHEEL
tripo3d-0.3.10.dist-info/top_level.txt
tripo3d-0.3.10.dist-info/RECORD
