Metadata-Version: 2.4
Name: tripo3d
Version: 0.3.10
Summary: Python client for the Tripo 3D Generation API
Author: Tripo Development Team
License: MIT
Project-URL: Homepage, https://github.com/VAST-AI-Research/tripo-python-sdk
Project-URL: Bug Tracker, https://github.com/VAST-AI-Research/tripo-python-sdk/issues
Keywords: tripo,3d,generation,ai,model,api
Classifier: Programming Language :: Python :: 3
Classifier: Programming Language :: Python :: 3.8
Classifier: Programming Language :: Python :: 3.9
Classifier: Programming Language :: Python :: 3.10
Classifier: Programming Language :: Python :: 3.11
Classifier: License :: OSI Approved :: MIT License
Classifier: Operating System :: OS Independent
Classifier: Development Status :: 4 - Beta
Classifier: Intended Audience :: Developers
Classifier: Topic :: Software Development :: Libraries :: Python Modules
Classifier: Topic :: Multimedia :: Graphics :: 3D Modeling
Requires-Python: >=3.8
License-File: LICENSE
Provides-Extra: async
Requires-Dist: aiohttp>=3.8.0; extra == "async"
Provides-Extra: s3
Requires-Dist: boto3>=1.20.0; extra == "s3"
Dynamic: license-file
